pydamo_0/__init__.py
pydamo_0/cleaners.py
pydamo_0/damo.py
pydamo_0/dm.dll
pydamo_0/enum_wind.py
pydamo_0/extractor.py
pydamo_0/regsvr.py
pydamo_0/titles.py
pydamo_test-1.0.0.data/data/dm.dll
pydamo_test-1.0.0.dist-info/LICENSE.txt
pydamo_test-1.0.0.dist-info/METADATA
pydamo_test-1.0.0.dist-info/WHEEL
pydamo_test-1.0.0.dist-info/top_level.txt
pydamo_test-1.0.0.dist-info/RECORD
