Metadata-Version: 2.1
Name: pydamo-test
Version: 1.0.0
Summary: pydamo with dm.dll and auto-regsvr
Home-page: https://github.com/bode135/pydamo
Author: bode135
Author-email: 2248270222@qq.com
License: UNKNOWN
Platform: UNKNOWN
Classifier: Programming Language :: Python :: 3
Classifier: License :: OSI Approved :: MIT License
Classifier: Operating System :: OS Independent
Requires-Python: >=3.6
Requires-Dist: pywin32
Requires-Dist: bode-time
